{"cameraMode":{"drawMode":0,"name":"Shaded","section":"Shading Mode"},"sceneLighting":false,"audioPlay":false,"sceneViewState":{"m_AlwaysRefresh":false,"showFog":true,"showSkybox":false,"showFlares":true,"showImageEffects":true,"showParticleSystems":true,"showVisualEffectGraphs":true,"m_FxEnabled":true},"in2DMode":false,"pivot":{"x":417.63690185546877,"y":201.76551818847657,"z":0.0},"rotation":{"x":-0.18696731328964234,"y":-0.010607362724840641,"z":-0.0020518507808446886,"w":0.982285737991333},"size":13.03855037689209,"orthographic":false}